<?xml version="1.0" encoding="utf-8"?><index><!-- saved from url=(0014)about:internet -->
<stem n="talker"><phr n="talkers"><ent r="3" t="2" w="782" /><ent r="4" t="113" w="76" /><ent r="4" t="114" w="355" /><ent r="3" t="114" w="564" /><ent r="6" t="114" w="748" /><ent r="6" t="114" w="770" /><ent r="4" t="115" w="28" /></phr><phr n="talker"><ent r="4" t="115" w="865" /><ent r="4" t="115" w="877" /></phr></stem><stem n="port"><phr n="ports"><ent r="3" t="2" w="784" /><ent r="4" t="13" w="77" /><ent r="3" t="15" w="662" /><ent r="4" t="20" w="39" /><ent r="4" t="20" w="50" /><ent r="4" t="35" w="202" /><ent r="4" t="41" w="388" /><ent r="100" t="41" w="421" /><ent r="100" t="41" w="424" /><ent r="100" t="41" w="427" /><ent r="65" t="41" w="435" /><ent r="4" t="41" w="554" /><ent r="1000" t="42" w="5" /><ent r="100" t="42" w="22" /><ent r="102" t="42" w="28" /><ent r="100" t="42" w="45" /><ent r="100" t="42" w="48" /><ent r="100" t="42" w="51" /><ent r="92" t="42" w="56" /><ent r="3" t="42" w="67" /><ent r="3" t="42" w="168" /><ent r="4" t="42" w="173" /><ent r="4" t="42" w="210" /><ent r="92" t="42" w="223" /><ent r="6" t="42" w="311" /><ent r="7" t="42" w="412" /><ent r="3" t="53" w="934" /><ent r="3" t="65" w="852" /><ent r="3" t="65" w="868" /><ent r="5" t="68" w="890" /><ent r="5" t="68" w="906" /><ent r="3" t="89" w="632" /><ent r="5" t="114" w="274" /><ent r="5" t="114" w="301" /><ent r="66" t="114" w="372" /><ent r="4" t="114" w="379" /><ent r="3" t="114" w="566" /><ent r="68" t="114" w="847" /><ent r="6" t="114" w="1239" /><ent r="4" t="115" w="826" /><ent r="4" t="115" w="848" /><ent r="5" t="115" w="1039" /><ent r="1000" t="116" w="2" /><ent r="102" t="116" w="6" /><ent r="5" t="116" w="13" /><ent r="4" t="116" w="27" /><ent r="3" t="116" w="51" /><ent r="3" t="116" w="63" /><ent r="4" t="116" w="257" /><ent r="82" t="116" w="390" /><ent r="3" t="116" w="395" /><ent r="3" t="116" w="405" /><ent r="4" t="116" w="715" /><ent r="4" t="116" w="727" /><ent r="4" t="116" w="747" /><ent r="82" t="116" w="828" /><ent r="3" t="116" w="844" /><ent r="4" t="116" w="921" /><ent r="4" t="120" w="593" /><ent r="3" t="121" w="114" /><ent r="3" t="121" w="152" /><ent r="4" t="122" w="193" /><ent r="5" t="122" w="277" /><ent r="4" t="122" w="285" /><ent r="4" t="122" w="645" /><ent r="4" t="122" w="655" /><ent r="4" t="122" w="664" /><ent r="4" t="122" w="770" /><ent r="3" t="123" w="29" /><ent r="4" t="123" w="309" /><ent r="4" t="123" w="314" /><ent r="4" t="123" w="336" /><ent r="4" t="123" w="351" /><ent r="3" t="124" w="25" /><ent r="4" t="124" w="81" /><ent r="4" t="124" w="92" /><ent r="4" t="124" w="224" /><ent r="6" t="125" w="73" /><ent r="6" t="125" w="230" /><ent r="6" t="125" w="249" /><ent r="5" t="140" w="1401" /><ent r="5" t="140" w="1496" /><ent r="5" t="140" w="1595" /><ent r="5" t="140" w="1699" /><ent r="4" t="165" w="1974" /><ent r="3" t="205" w="1853" /><ent r="3" t="211" w="394" /><ent r="4" t="211" w="967" /><ent r="4" t="211" w="1226" /><ent r="4" t="211" w="1256" /></phr><phr n="porting"><ent r="3" t="5" w="2005" /></phr><phr n="port"><ent r="4" t="13" w="100" /><ent r="4" t="13" w="104" /><ent r="6" t="14" w="1712" /><ent r="100" t="16" w="348" /><ent r="4" t="16" w="357" /><ent r="4" t="18" w="224" /><ent r="100" t="28" w="449" /><ent r="100" t="28" w="456" /><ent r="100" t="28" w="458" /><ent r="5" t="28" w="460" /><ent r="100" t="30" w="591" /><ent r="4" t="30" w="637" /><ent r="3" t="31" w="169" /><ent r="3" t="31" w="210" /><ent r="5" t="31" w="241" /><ent r="4" t="31" w="245" /><ent r="4" t="41" w="539" /><ent r="3" t="42" w="100" /><ent r="3" t="42" w="237" /><ent r="3" t="42" w="254" /><ent r="3" t="42" w="259" /><ent r="3" t="42" w="275" /><ent r="3" t="42" w="297" /><ent r="7" t="42" w="364" /><ent r="7" t="42" w="382" /><ent r="7" t="42" w="388" /><ent r="7" t="42" w="397" /><ent r="7" t="42" w="423" /><ent r="7" t="42" w="428" /><ent r="4" t="53" w="465" /><ent r="100" t="56" w="213" /><ent r="4" t="56" w="223" /><ent r="4" t="56" w="229" /><ent r="6" t="56" w="236" /><ent r="4" t="56" w="251" /><ent r="5" t="57" w="292" /><ent r="3" t="65" w="774" /><ent r="5" t="68" w="870" /><ent r="5" t="68" w="887" /><ent r="3" t="70" w="61" /><ent r="3" t="70" w="69" /><ent r="100" t="70" w="145" /><ent r="3" t="70" w="156" /><ent r="3" t="83" w="378" /><ent r="3" t="83" w="391" /><ent r="3" t="83" w="409" /><ent r="3" t="83" w="431" /><ent r="3" t="83" w="465" /><ent r="3" t="83" w="477" /><ent r="3" t="83" w="505" /><ent r="3" t="83" w="516" /><ent r="3" t="83" w="531" /><ent r="3" t="83" w="557" /><ent r="3" t="83" w="568" /><ent r="100" t="89" w="5" /><ent r="5" t="89" w="884" /><ent r="4" t="89" w="905" /><ent r="5" t="89" w="915" /><ent r="4" t="89" w="927" /><ent r="4" t="89" w="931" /><ent r="4" t="89" w="939" /><ent r="4" t="89" w="950" /><ent r="4" t="89" w="961" /><ent r="100" t="92" w="99" /><ent r="4" t="92" w="128" /><ent r="4" t="92" w="134" /><ent r="4" t="92" w="173" /><ent r="3" t="99" w="344" /><ent r="4" t="102" w="303" /><ent r="3" t="102" w="513" /><ent r="3" t="103" w="213" /><ent r="3" t="104" w="141" /><ent r="3" t="104" w="145" /><ent r="4" t="104" w="248" /><ent r="3" t="104" w="420" /><ent r="4" t="105" w="210" /><ent r="3" t="105" w="315" /><ent r="7" t="108" w="1185" /><ent r="4" t="114" w="262" /><ent r="4" t="114" w="283" /><ent r="4" t="114" w="313" /><ent r="6" t="114" w="690" /><ent r="6" t="114" w="694" /><ent r="6" t="114" w="704" /><ent r="6" t="114" w="719" /><ent r="6" t="114" w="858" /><ent r="7" t="114" w="876" /><ent r="5" t="115" w="1042" /><ent r="5" t="115" w="1065" /><ent r="5" t="115" w="1069" /><ent r="3" t="116" w="67" /><ent r="3" t="116" w="78" /><ent r="4" t="116" w="106" /><ent r="4" t="116" w="119" /><ent r="4" t="116" w="139" /><ent r="3" t="116" w="239" /><ent r="4" t="116" w="268" /><ent r="4" t="116" w="295" /><ent r="5" t="116" w="352" /><ent r="5" t="116" w="356" /><ent r="4" t="116" w="369" /><ent r="5" t="116" w="512" /><ent r="4" t="116" w="767" /><ent r="4" t="116" w="781" /><ent r="6" t="116" w="783" /><ent r="4" t="116" w="786" /><ent r="4" t="116" w="818" /><ent r="5" t="116" w="860" /><ent r="4" t="116" w="868" /><ent r="5" t="116" w="871" /><ent r="4" t="116" w="878" /><ent r="5" t="116" w="901" /><ent r="4" t="116" w="909" /><ent r="5" t="116" w="912" /><ent r="4" t="116" w="919" /><ent r="5" t="116" w="937" /><ent r="4" t="116" w="947" /><ent r="5" t="116" w="951" /><ent r="4" t="116" w="1003" /><ent r="6" t="118" w="120" /><ent r="5" t="118" w="123" /><ent r="6" t="118" w="133" /><ent r="5" t="118" w="136" /><ent r="5" t="119" w="190" /><ent r="5" t="120" w="572" /><ent r="4" t="120" w="586" /><ent r="4" t="120" w="591" /><ent r="5" t="120" w="630" /><ent r="4" t="120" w="639" /><ent r="4" t="120" w="642" /><ent r="4" t="120" w="652" /><ent r="4" t="120" w="657" /><ent r="5" t="120" w="749" /><ent r="4" t="120" w="758" /><ent r="4" t="120" w="767" /><ent r="4" t="120" w="779" /><ent r="4" t="120" w="829" /><ent r="4" t="121" w="48" /><ent r="4" t="121" w="62" /><ent r="3" t="121" w="219" /><ent r="4" t="122" w="500" /><ent r="4" t="122" w="606" /><ent r="4" t="123" w="67" /><ent r="5" t="123" w="83" /><ent r="4" t="123" w="89" /><ent r="4" t="123" w="126" /><ent r="4" t="123" w="216" /><ent r="3" t="123" w="392" /><ent r="5" t="124" w="72" /><ent r="4" t="124" w="293" /><ent r="6" t="125" w="94" /><ent r="6" t="125" w="127" /><ent r="6" t="125" w="155" /><ent r="6" t="125" w="162" /><ent r="6" t="125" w="196" /><ent r="6" t="125" w="267" /><ent r="6" t="125" w="272" /><ent r="6" t="125" w="282" /><ent r="6" t="125" w="297" /><ent r="6" t="125" w="393" /><ent r="6" t="125" w="415" /><ent r="6" t="125" w="417" /><ent r="6" t="125" w="531" /><ent r="6" t="125" w="565" /><ent r="6" t="125" w="608" /><ent r="3" t="125" w="901" /><ent r="6" t="125" w="930" /><ent r="6" t="125" w="954" /><ent r="6" t="125" w="965" /><ent r="7" t="135" w="508" /><ent r="4" t="139" w="577" /><ent r="100" t="140" w="1260" /><ent r="6" t="140" w="1263" /><ent r="100" t="140" w="1265" /><ent r="5" t="140" w="1273" /><ent r="5" t="140" w="1452" /><ent r="5" t="140" w="1551" /><ent r="5" t="140" w="1652" /><ent r="5" t="140" w="1763" /><ent r="5" t="140" w="1774" /><ent r="5" t="140" w="1825" /><ent r="5" t="140" w="1871" /><ent r="5" t="140" w="1916" /><ent r="5" t="140" w="1921" /><ent r="3" t="147" w="616" /><ent r="4" t="147" w="655" /><ent r="4" t="147" w="688" /><ent r="5" t="150" w="1401" /><ent r="4" t="150" w="1408" /><ent r="5" t="150" w="1509" /><ent r="4" t="150" w="1516" /><ent r="5" t="150" w="1621" /><ent r="4" t="150" w="1628" /><ent r="5" t="151" w="819" /><ent r="4" t="151" w="825" /><ent r="4" t="152" w="716" /><ent r="4" t="154" w="296" /><ent r="4" t="154" w="509" /><ent r="4" t="154" w="515" /><ent r="4" t="154" w="525" /><ent r="4" t="154" w="623" /><ent r="4" t="154" w="642" /><ent r="4" t="154" w="756" /><ent r="4" t="154" w="775" /><ent r="4" t="154" w="886" /><ent r="4" t="154" w="905" /><ent r="4" t="154" w="1021" /><ent r="4" t="154" w="1040" /><ent r="4" t="154" w="1156" /><ent r="4" t="154" w="1175" /><ent r="4" t="154" w="1292" /><ent r="4" t="154" w="1311" /><ent r="4" t="154" w="1427" /><ent r="4" t="154" w="1446" /><ent r="4" t="154" w="1591" /><ent r="4" t="154" w="1639" /><ent r="4" t="154" w="1891" /><ent r="4" t="154" w="1910" /><ent r="4" t="154" w="2145" /><ent r="4" t="154" w="2236" /><ent r="4" t="154" w="2332" /><ent r="5" t="154" w="2598" /><ent r="4" t="154" w="2605" /><ent r="5" t="154" w="3364" /><ent r="4" t="154" w="3371" /><ent r="4" t="154" w="4290" /><ent r="5" t="154" w="4434" /><ent r="4" t="154" w="4438" /><ent r="5" t="154" w="4527" /><ent r="4" t="154" w="4531" /><ent r="4" t="154" w="4592" /><ent r="4" t="154" w="4598" /><ent r="4" t="154" w="4651" /><ent r="4" t="154" w="4718" /><ent r="4" t="154" w="4802" /><ent r="4" t="154" w="4841" /><ent r="4" t="154" w="4861" /><ent r="4" t="154" w="4915" /><ent r="4" t="155" w="408" /><ent r="4" t="155" w="445" /><ent r="4" t="155" w="520" /><ent r="4" t="155" w="526" /><ent r="4" t="155" w="779" /><ent r="4" t="155" w="825" /><ent r="4" t="155" w="835" /><ent r="4" t="155" w="2578" /><ent r="4" t="155" w="2585" /><ent r="4" t="155" w="2598" /><ent r="4" t="155" w="2744" /><ent r="4" t="155" w="2751" /><ent r="4" t="155" w="2764" /><ent r="4" t="155" w="2866" /><ent r="4" t="155" w="2872" /><ent r="4" t="155" w="3300" /><ent r="4" t="155" w="3306" /><ent r="4" t="155" w="3628" /><ent r="4" t="155" w="3634" /><ent r="4" t="155" w="3842" /><ent r="4" t="155" w="3848" /><ent r="4" t="155" w="4151" /><ent r="4" t="155" w="4157" /><ent r="4" t="155" w="4390" /><ent r="4" t="155" w="4396" /><ent r="4" t="155" w="4685" /><ent r="4" t="155" w="4691" /><ent r="4" t="155" w="5007" /><ent r="4" t="155" w="5013" /><ent r="4" t="155" w="5243" /><ent r="4" t="155" w="5249" /><ent r="4" t="155" w="5479" /><ent r="4" t="155" w="5485" /><ent r="4" t="155" w="5727" /><ent r="4" t="155" w="5733" /><ent r="4" t="155" w="6615" /><ent r="4" t="155" w="6621" /><ent r="4" t="155" w="6687" /><ent r="4" t="155" w="6694" /><ent r="4" t="155" w="6792" /><ent r="4" t="155" w="6798" /><ent r="4" t="155" w="6899" /><ent r="4" t="155" w="6906" /><ent r="4" t="155" w="7083" /><ent r="4" t="155" w="7089" /><ent r="4" t="155" w="7685" /><ent r="4" t="155" w="7692" /><ent r="4" t="155" w="7820" /><ent r="4" t="155" w="7826" /><ent r="4" t="155" w="7945" /><ent r="4" t="155" w="8159" /><ent r="4" t="155" w="8165" /><ent r="4" t="155" w="8332" /><ent r="4" t="155" w="8379" /><ent r="4" t="155" w="8385" /><ent r="4" t="155" w="8570" /><ent r="4" t="155" w="8581" /><ent r="4" t="155" w="8819" /><ent r="4" t="155" w="8825" /><ent r="4" t="155" w="8949" /><ent r="4" t="155" w="8955" /><ent r="4" t="155" w="8967" /><ent r="4" t="155" w="9230" /><ent r="4" t="155" w="9436" /><ent r="4" t="155" w="9442" /><ent r="5" t="157" w="2770" /><ent r="4" t="157" w="2779" /><ent r="5" t="157" w="2897" /><ent r="4" t="157" w="2906" /><ent r="5" t="157" w="3031" /><ent r="4" t="157" w="3039" /><ent r="5" t="157" w="3120" /><ent r="4" t="157" w="3128" /><ent r="5" t="157" w="3270" /><ent r="4" t="157" w="3278" /><ent r="5" t="157" w="3352" /><ent r="4" t="157" w="3360" /><ent r="5" t="157" w="3495" /><ent r="4" t="157" w="3503" /><ent r="4" t="159" w="377" /><ent r="3" t="162" w="1536" /><ent r="3" t="162" w="1539" /><ent r="3" t="162" w="1542" /><ent r="3" t="162" w="1546" /><ent r="5" t="164" w="136" /><ent r="4" t="164" w="140" /><ent r="4" t="164" w="149" /><ent r="4" t="164" w="155" /><ent r="4" t="164" w="173" /><ent r="3" t="164" w="354" /><ent r="3" t="164" w="368" /><ent r="3" t="164" w="376" /><ent r="3" t="164" w="384" /><ent r="4" t="165" w="1965" /><ent r="4" t="165" w="2024" /><ent r="4" t="165" w="2043" /><ent r="5" t="166" w="647" /><ent r="5" t="167" w="311" /><ent r="3" t="182" w="697" /><ent r="5" t="185" w="761" /><ent r="5" t="185" w="1273" /><ent r="5" t="185" w="1296" /><ent r="5" t="185" w="1300" /><ent r="3" t="193" w="228" /><ent r="3" t="194" w="266" /><ent r="6" t="194" w="317" /><ent r="3" t="194" w="694" /><ent r="3" t="194" w="700" /><ent r="4" t="197" w="404" /><ent r="3" t="202" w="572" /><ent r="3" t="202" w="1417" /><ent r="3" t="202" w="1438" /><ent r="3" t="202" w="1473" /><ent r="3" t="202" w="1968" /><ent r="3" t="202" w="2040" /><ent r="3" t="202" w="2108" /><ent r="3" t="202" w="2124" /><ent r="3" t="202" w="2239" /><ent r="3" t="202" w="2246" /><ent r="3" t="202" w="2253" /><ent r="3" t="202" w="2260" /><ent r="3" t="202" w="2267" /><ent r="3" t="202" w="2274" /><ent r="6" t="203" w="203" /><ent r="5" t="203" w="214" /><ent r="100" t="204" w="57" /><ent r="6" t="204" w="88" /><ent r="6" t="204" w="89" /><ent r="100" t="204" w="97" /><ent r="6" t="204" w="105" /><ent r="3" t="211" w="218" /><ent r="5" t="211" w="1071" /><ent r="3" t="211" w="1536" /><ent r="3" t="211" w="1565" /><ent r="3" t="211" w="1572" /><ent r="92" t="213" w="879" /><ent r="3" t="213" w="890" /><ent r="3" t="213" w="918" /><ent r="4" t="221" w="911" /><ent r="4" t="221" w="916" /><ent r="4" t="221" w="929" /></phr></stem><stem n="session"><phr n="sessions"><ent r="3" t="2" w="787" /><ent r="4" t="113" w="88" /><ent r="66" t="114" w="422" /><ent r="4" t="114" w="429" /><ent r="3" t="114" w="568" /><ent r="68" t="114" w="852" /><ent r="6" t="114" w="1242" /><ent r="5" t="115" w="1089" /><ent r="4" t="115" w="1094" /><ent r="1000" t="118" w="2" /><ent r="102" t="118" w="6" /><ent r="5" t="118" w="13" /><ent r="4" t="118" w="27" /><ent r="3" t="118" w="47" /><ent r="3" t="118" w="54" /><ent r="82" t="118" w="365" /><ent r="3" t="118" w="372" /><ent r="4" t="118" w="381" /><ent r="3" t="213" w="801" /><ent r="3" t="214" w="19" /><ent r="3" t="214" w="36" /></phr><phr n="session"><ent r="4" t="113" w="91" /><ent r="4" t="114" w="444" /><ent r="4" t="118" w="42" /><ent r="5" t="118" w="74" /><ent r="5" t="118" w="90" /><ent r="5" t="118" w="102" /><ent r="5" t="118" w="117" /><ent r="5" t="118" w="128" /><ent r="5" t="118" w="141" /><ent r="5" t="118" w="156" /><ent r="5" t="118" w="172" /><ent r="5" t="118" w="188" /><ent r="5" t="118" w="204" /><ent r="5" t="118" w="220" /><ent r="5" t="118" w="226" /><ent r="5" t="118" w="232" /><ent r="5" t="118" w="268" /><ent r="5" t="118" w="271" /><ent r="5" t="118" w="305" /><ent r="4" t="120" w="1064" /><ent r="4" t="120" w="1066" /><ent r="4" t="120" w="1111" /><ent r="4" t="120" w="1165" /><ent r="6" t="120" w="1251" /><ent r="3" t="120" w="1319" /><ent r="3" t="137" w="772" /><ent r="4" t="154" w="566" /><ent r="5" t="155" w="8677" /><ent r="3" t="202" w="469" /><ent r="3" t="202" w="1881" /><ent r="3" t="213" w="658" /><ent r="3" t="213" w="734" /><ent r="3" t="213" w="755" /><ent r="3" t="213" w="787" /></phr></stem><stem n=".0.5."><phr n=".0.5."><ent r="3" t="2" w="794" /></phr></stem><stem n="v2"><phr n="v2"><ent r="3" t="2" w="807" /><ent r="65" t="148" w="852" /><ent r="4" t="151" w="275" /><ent r="4" t="151" w="427" /><ent r="4" t="151" w="653" /><ent r="65" t="155" w="220" /><ent r="92" t="155" w="5920" /></phr></stem><stem n="bit"><phr n="bits"><ent r="3" t="2" w="817" /><ent r="3" t="22" w="384" /><ent r="3" t="22" w="425" /><ent r="100" t="53" w="480" /><ent r="6" t="53" w="482" /><ent r="4" t="53" w="500" /><ent r="4" t="53" w="502" /><ent r="4" t="53" w="514" /><ent r="6" t="54" w="309" /><ent r="6" t="54" w="313" /><ent r="4" t="55" w="287" /><ent r="4" t="55" w="289" /><ent r="5" t="57" w="296" /><ent r="3" t="65" w="635" /><ent r="4" t="70" w="306" /><ent r="5" t="120" w="930" /><ent r="5" t="120" w="940" /><ent r="5" t="185" w="1926" /><ent r="5" t="187" w="512" /><ent r="3" t="205" w="922" /><ent r="3" t="205" w="932" /><ent r="3" t="205" w="952" /><ent r="3" t="205" w="971" /><ent r="3" t="205" w="993" /><ent r="3" t="205" w="998" /><ent r="3" t="205" w="1122" /><ent r="3" t="208" w="796" /><ent r="3" t="208" w="798" /><ent r="6" t="209" w="65" /><ent r="6" t="209" w="74" /><ent r="6" t="209" w="144" /></phr><phr n="bit"><ent r="3" t="12" w="188" /><ent r="6" t="12" w="229" /><ent r="6" t="12" w="250" /><ent r="7" t="43" w="423" /><ent r="4" t="53" w="517" /><ent r="100" t="89" w="208" /><ent r="4" t="89" w="226" /><ent r="5" t="109" w="187" /><ent r="5" t="109" w="194" /><ent r="100" t="112" w="442" /><ent r="4" t="112" w="460" /><ent r="3" t="112" w="766" /><ent r="4" t="120" w="1135" /><ent r="4" t="151" w="698" /><ent r="3" t="165" w="1173" /><ent r="5" t="175" w="207" /><ent r="5" t="175" w="217" /><ent r="5" t="175" w="472" /><ent r="5" t="175" w="483" /><ent r="5" t="175" w="637" /><ent r="5" t="175" w="646" /><ent r="5" t="175" w="691" /><ent r="5" t="175" w="712" /><ent r="9" t="175" w="736" /><ent r="9" t="175" w="778" /><ent r="9" t="175" w="816" /><ent r="5" t="187" w="769" /><ent r="3" t="208" w="28" /><ent r="3" t="208" w="60" /><ent r="3" t="208" w="231" /><ent r="3" t="208" w="272" /><ent r="100" t="208" w="763" /><ent r="100" t="208" w="770" /><ent r="3" t="208" w="819" /><ent r="100" t="208" w="1338" /><ent r="100" t="208" w="1344" /><ent r="100" t="208" w="1347" /><ent r="4" t="208" w="1358" /><ent r="4" t="208" w="1364" /><ent r="4" t="208" w="1372" /><ent r="3" t="209" w="192" /></phr></stem><stem n="byte"><phr n="bytes"><ent r="3" t="2" w="819" /><ent r="100" t="33" w="4" /><ent r="6" t="33" w="767" /><ent r="100" t="33" w="804" /><ent r="4" t="33" w="812" /><ent r="3" t="65" w="488" /><ent r="3" t="83" w="1938" /><ent r="5" t="115" w="421" /><ent r="5" t="115" w="899" /><ent r="4" t="115" w="906" /><ent r="4" t="115" w="939" /><ent r="4" t="115" w="953" /><ent r="4" t="115" w="966" /><ent r="4" t="115" w="990" /><ent r="5" t="116" w="514" /><ent r="5" t="116" w="789" /><ent r="4" t="116" w="796" /><ent r="5" t="117" w="206" /><ent r="5" t="117" w="389" /><ent r="4" t="117" w="396" /><ent r="6" t="118" w="105" /><ent r="5" t="118" w="111" /><ent r="6" t="118" w="175" /><ent r="5" t="118" w="181" /><ent r="6" t="118" w="207" /><ent r="5" t="118" w="213" /><ent r="5" t="120" w="931" /><ent r="5" t="120" w="944" /><ent r="4" t="129" w="299" /><ent r="5" t="149" w="332" /><ent r="4" t="149" w="337" /><ent r="4" t="149" w="346" /><ent r="4" t="149" w="356" /><ent r="4" t="149" w="361" /><ent r="4" t="149" w="393" /><ent r="4" t="149" w="412" /><ent r="4" t="149" w="585" /><ent r="4" t="150" w="1530" /><ent r="5" t="150" w="2077" /><ent r="4" t="151" w="542" /><ent r="4" t="151" w="579" /><ent r="4" t="151" w="684" /><ent r="4" t="152" w="1170" /><ent r="4" t="152" w="1199" /><ent r="4" t="152" w="1349" /><ent r="4" t="152" w="1379" /><ent r="4" t="156" w="1280" /><ent r="4" t="157" w="1639" /><ent r="4" t="157" w="6171" /><ent r="4" t="157" w="6982" /><ent r="4" t="158" w="401" /><ent r="4" t="158" w="409" /><ent r="4" t="158" w="414" /><ent r="4" t="158" w="426" /><ent r="4" t="158" w="433" /><ent r="4" t="158" w="446" /><ent r="4" t="158" w="465" /><ent r="4" t="158" w="470" /><ent r="100" t="165" w="5" /><ent r="100" t="165" w="1200" /><ent r="3" t="165" w="1209" /><ent r="4" t="165" w="1422" /><ent r="3" t="165" w="2198" /><ent r="5" t="197" w="262" /><ent r="4" t="197" w="430" /><ent r="4" t="197" w="458" /><ent r="70" t="200" w="125" /><ent r="3" t="202" w="971" /><ent r="3" t="202" w="1110" /><ent r="3" t="202" w="1155" /><ent r="3" t="211" w="206" /></phr><phr n="byte"><ent r="4" t="103" w="740" /><ent r="4" t="103" w="748" /><ent r="4" t="149" w="381" /><ent r="100" t="165" w="53" /><ent r="65" t="165" w="147" /><ent r="100" t="165" w="1338" /><ent r="100" t="165" w="1342" /><ent r="4" t="165" w="1349" /><ent r="92" t="165" w="2188" /><ent r="8" t="196" w="385" /><ent r="8" t="196" w="401" /><ent r="100" t="196" w="591" /><ent r="8" t="196" w="594" /><ent r="8" t="196" w="670" /></phr></stem><stem n="per"><phr n="per"><ent r="3" t="2" w="820" /><ent r="6" t="14" w="1598" /><ent r="7" t="14" w="1664" /><ent r="4" t="23" w="1190" /><ent r="4" t="28" w="694" /><ent r="4" t="28" w="708" /><ent r="100" t="33" w="5" /><ent r="6" t="33" w="762" /><ent r="6" t="33" w="768" /><ent r="100" t="33" w="785" /><ent r="4" t="33" w="793" /><ent r="100" t="33" w="805" /><ent r="4" t="33" w="813" /><ent r="100" t="33" w="826" /><ent r="4" t="33" w="834" /><ent r="3" t="36" w="723" /><ent r="3" t="53" w="296" /><ent r="4" t="70" w="307" /><ent r="100" t="74" w="176" /><ent r="4" t="74" w="185" /><ent r="4" t="79" w="834" /><ent r="3" t="110" w="155" /><ent r="3" t="110" w="177" /><ent r="5" t="120" w="393" /><ent r="4" t="120" w="532" /><ent r="3" t="133" w="107" /><ent r="4" t="138" w="1826" /><ent r="4" t="138" w="1850" /><ent r="4" t="138" w="1873" /><ent r="5" t="140" w="1384" /><ent r="5" t="140" w="1414" /><ent r="5" t="140" w="1431" /><ent r="5" t="140" w="1459" /><ent r="5" t="140" w="1478" /><ent r="5" t="140" w="1508" /><ent r="5" t="140" w="1527" /><ent r="5" t="140" w="1558" /><ent r="5" t="140" w="1578" /><ent r="5" t="140" w="1608" /><ent r="5" t="140" w="1628" /><ent r="5" t="140" w="1659" /><ent r="5" t="140" w="1681" /><ent r="5" t="140" w="1714" /><ent r="5" t="140" w="1736" /><ent r="5" t="140" w="1770" /><ent r="5" t="140" w="1783" /><ent r="5" t="140" w="1799" /><ent r="5" t="140" w="1821" /><ent r="5" t="140" w="1838" /><ent r="5" t="140" w="1856" /><ent r="5" t="140" w="1884" /><ent r="5" t="140" w="1901" /><ent r="5" t="140" w="1928" /><ent r="4" t="150" w="1424" /><ent r="4" t="150" w="1531" /><ent r="4" t="152" w="1102" /><ent r="4" t="152" w="1134" /><ent r="4" t="152" w="1281" /><ent r="4" t="152" w="1313" /><ent r="4" t="157" w="9606" /><ent r="4" t="158" w="246" /><ent r="4" t="158" w="266" /><ent r="4" t="158" w="287" /><ent r="4" t="158" w="299" /><ent r="4" t="158" w="326" /><ent r="4" t="158" w="349" /><ent r="4" t="158" w="416" /><ent r="3" t="165" w="2265" /><ent r="3" t="165" w="2268" /><ent r="4" t="172" w="110" /><ent r="5" t="187" w="513" /><ent r="5" t="197" w="254" /><ent r="5" t="197" w="263" /><ent r="4" t="197" w="431" /><ent r="4" t="197" w="437" /><ent r="4" t="197" w="459" /><ent r="4" t="197" w="465" /><ent r="3" t="202" w="962" /><ent r="3" t="202" w="972" /><ent r="3" t="202" w="1100" /><ent r="3" t="202" w="1111" /><ent r="3" t="202" w="1122" /><ent r="3" t="202" w="1133" /><ent r="3" t="202" w="1145" /><ent r="3" t="202" w="1156" /><ent r="3" t="202" w="1167" /><ent r="3" t="202" w="1178" /></phr></stem><stem n="second"><phr n="second"><ent r="3" t="2" w="821" /><ent r="3" t="22" w="153" /><ent r="4" t="23" w="1191" /><ent r="100" t="33" w="6" /><ent r="6" t="33" w="763" /><ent r="6" t="33" w="769" /><ent r="100" t="33" w="786" /><ent r="4" t="33" w="794" /><ent r="4" t="41" w="159" /><ent r="3" t="47" w="90" /><ent r="3" t="47" w="518" /><ent r="3" t="47" w="537" /><ent r="3" t="47" w="545" /><ent r="3" t="47" w="553" /><ent r="3" t="49" w="478" /><ent r="4" t="70" w="308" /><ent r="4" t="89" w="924" /><ent r="4" t="115" w="218" /><ent r="4" t="115" w="221" /><ent r="4" t="116" w="200" /><ent r="4" t="116" w="203" /><ent r="4" t="123" w="199" /><ent r="4" t="129" w="300" /><ent r="4" t="136" w="547" /><ent r="4" t="149" w="586" /><ent r="4" t="149" w="588" /><ent r="4" t="150" w="1375" /><ent r="4" t="150" w="1425" /><ent r="4" t="150" w="1532" /><ent r="5" t="150" w="2078" /><ent r="4" t="151" w="685" /><ent r="4" t="151" w="687" /><ent r="5" t="151" w="1188" /><ent r="5" t="155" w="9576" /><ent r="4" t="155" w="9586" /><ent r="4" t="155" w="9618" /><ent r="4" t="158" w="236" /><ent r="4" t="158" w="247" /><ent r="4" t="158" w="267" /><ent r="4" t="158" w="288" /><ent r="3" t="159" w="218" /><ent r="3" t="159" w="221" /><ent r="6" t="162" w="611" /><ent r="100" t="165" w="6" /><ent r="100" t="165" w="54" /><ent r="100" t="165" w="1201" /><ent r="3" t="165" w="1210" /><ent r="100" t="165" w="1216" /><ent r="3" t="165" w="1223" /><ent r="100" t="165" w="1339" /><ent r="100" t="165" w="1343" /><ent r="4" t="165" w="1350" /><ent r="4" t="165" w="1423" /><ent r="3" t="165" w="2266" /><ent r="4" t="182" w="391" /><ent r="5" t="187" w="514" /><ent r="3" t="194" w="689" /><ent r="100" t="196" w="576" /><ent r="8" t="196" w="579" /><ent r="100" t="196" w="592" /><ent r="8" t="196" w="595" /><ent r="8" t="196" w="660" /><ent r="8" t="196" w="671" /><ent r="5" t="197" w="255" /><ent r="5" t="197" w="264" /><ent r="3" t="197" w="359" /><ent r="4" t="197" w="432" /><ent r="4" t="197" w="460" /><ent r="3" t="202" w="963" /><ent r="3" t="202" w="973" /><ent r="3" t="202" w="1101" /><ent r="3" t="202" w="1112" /><ent r="3" t="202" w="1146" /><ent r="3" t="202" w="1157" /><ent r="3" t="202" w="1447" /><ent r="4" t="208" w="1361" /><ent r="4" t="208" w="1394" /><ent r="3" t="211" w="1460" /><ent r="3" t="214" w="45" /></phr><phr n="seconds"><ent r="4" t="23" w="1207" /><ent r="4" t="53" w="560" /><ent r="4" t="53" w="569" /><ent r="4" t="74" w="139" /><ent r="4" t="83" w="133" /><ent r="4" t="83" w="142" /><ent r="4" t="83" w="155" /><ent r="4" t="120" w="1144" /><ent r="4" t="147" w="756" /><ent r="4" t="149" w="518" /><ent r="4" t="149" w="526" /><ent r="5" t="150" w="2072" /><ent r="5" t="151" w="1184" /><ent r="5" t="151" w="1190" /><ent r="4" t="154" w="2793" /><ent r="4" t="154" w="2810" /><ent r="4" t="154" w="2817" /><ent r="5" t="154" w="2860" /><ent r="5" t="154" w="2878" /><ent r="4" t="154" w="3559" /><ent r="4" t="154" w="3576" /><ent r="4" t="154" w="3583" /><ent r="5" t="154" w="3626" /><ent r="5" t="154" w="3644" /><ent r="5" t="154" w="4337" /><ent r="4" t="155" w="535" /><ent r="5" t="155" w="646" /><ent r="4" t="155" w="653" /><ent r="4" t="155" w="669" /><ent r="5" t="155" w="1242" /><ent r="4" t="155" w="1252" /><ent r="4" t="155" w="1293" /><ent r="4" t="155" w="7416" /><ent r="4" t="155" w="7620" /><ent r="4" t="155" w="7983" /><ent r="4" t="155" w="7988" /><ent r="5" t="155" w="8041" /><ent r="4" t="155" w="8050" /><ent r="4" t="155" w="8066" /><ent r="4" t="155" w="8076" /><ent r="4" t="156" w="957" /><ent r="4" t="156" w="1294" /><ent r="3" t="159" w="170" /><ent r="3" t="159" w="178" /><ent r="3" t="159" w="184" /><ent r="3" t="159" w="195" /><ent r="3" t="159" w="243" /><ent r="3" t="159" w="254" /><ent r="3" t="159" w="266" /><ent r="3" t="159" w="271" /><ent r="65" t="165" w="126" /><ent r="92" t="165" w="2149" /><ent r="4" t="182" w="510" /><ent r="5" t="185" w="1265" /><ent r="5" t="185" w="1768" /><ent r="5" t="185" w="2354" /><ent r="9" t="196" w="289" /><ent r="9" t="196" w="327" /><ent r="9" t="196" w="725" /><ent r="9" t="198" w="143" /><ent r="9" t="198" w="160" /><ent r="3" t="214" w="377" /><ent r="9" t="218" w="143" /><ent r="9" t="218" w="160" /></phr></stem></index>